pdf_scraper/__init__.py
pdf_scraper/scraper.py
pdf_scraper-0.1.0.dist-info/LICENSE
pdf_scraper-0.1.0.dist-info/METADATA
pdf_scraper-0.1.0.dist-info/WHEEL
pdf_scraper-0.1.0.dist-info/top_level.txt
pdf_scraper-0.1.0.dist-info/RECORD
