Metadata-Version: 2.1
Name: pdf-scraper
Version: 0.1.0
Summary: UNKNOWN
Home-page: https://github.com/bherbruck/pdf_scraper
Author: Brennen Herbruck
Author-email: brennen.herbruck@gmail.com
License: MIT
Platform: UNKNOWN
Requires-Python: >=3.6
Requires-Dist: six (==1.15.0)
Requires-Dist: pdfquery (==0.4.3)
